<?xml version="1.0"?>
<root>
<![CDATA[

Összesen:               38.360,- ███████
------------------------------------------------------
Kaja:                      810,- 

Pia:                     8.800,- █

Vonat:                   4.000,- 

Cigi:                    1.200,- 
Egyéb:                  23.550,- ████
------------------------------------------------------ Kaja
Kaja: 450,-
Kenyér: 200,-
Kenyér: 160,-
------------------------------------------------------ Pia
Depresszió koncerten: 2.500,-
Pia+kenyér: 2.000,-
Pia: 2.000,-
Kocsma: 1.300,-
7 db sör: 1.000,-
------------------------------------------------------ Vonat
Vonatjegyek haza és vissza Kb.: 4.000,-
------------------------------------------------------ Cigi
2 db Cigi: 1.200,-
------------------------------------------------------ Egyéb
WT havidíj: 10.000,-
Vizipipa, amit Benjinek fizetnek ki: 6.300,-
Ápiszban bevásárlás: 2.500,-
Depresszió koncertjegy: 2.000,-
Fahjés 250g Nakhla: 1.900,-
Tollak: 850,-

]]>
<MonthlySummary>38360</MonthlySummary>
<Eats>810</Eats>
<Booze>8800</Booze>
<Train>4000</Train>
<Cigarette>1200</Cigarette>
<Others>23550</Others>
</root>
